MANIFEST.in
README.rst
setup.py
collective/__init__.py
collective.portlet.rich.egg-info/PKG-INFO
collective.portlet.rich.egg-info/SOURCES.txt
collective.portlet.rich.egg-info/dependency_links.txt
collective.portlet.rich.egg-info/entry_points.txt
collective.portlet.rich.egg-info/namespace_packages.txt
collective.portlet.rich.egg-info/not-zip-safe
collective.portlet.rich.egg-info/requires.txt
collective.portlet.rich.egg-info/top_level.txt
collective/portlet/__init__.py
collective/portlet/rich/__init__.py
collective/portlet/rich/configure.zcml
collective/portlet/rich/richportlet.css
collective/portlet/rich/richportlet.pt
collective/portlet/rich/richportlet.py
collective/portlet/rich/richportlet.txt
collective/portlet/rich/vocabularies.py
collective/portlet/rich/locales/collective.portlet.rich.pot
collective/portlet/rich/locales/da/LC_MESSAGES/collective.portlet.rich.po
collective/portlet/rich/profiles/default/cssregistry.xml
collective/portlet/rich/profiles/default/portlets.xml
collective/portlet/rich/tests/__init__.py
collective/portlet/rich/tests/base.py
collective/portlet/rich/tests/test_functional_doctest.py
collective/portlet/rich/tests/test_portlet.py
docs/HISTORY.txt
docs/INSTALL.txt
docs/LICENSE.GPL
docs/LICENSE.txt