Metadata-Version: 1.1
Name: collective.portlet.rich
Version: 0.5
Summary: Rich-text portlet for Plone
Home-page: https://github.com/collective/collective.portlet.rich/
Author: Plone Foundation
Author-email: pellekrogholt@gmail.com
License: GPL
Platform: UNKNOWN
Classifier: Framework :: Plone
Classifier: Framework :: Zope2
Classifier: Framework :: Zope3
Classifier: Programming Language :: Python
Classifier: Topic :: Software Development :: Libraries :: Python Modules
